flasgger/__init__.py
flasgger/base.py
flasgger/commands.py
flasgger/constants.py
flasgger/marshmallow_apispec.py
flasgger/utils.py
flasgger/ui2/static/index.html
flasgger/ui2/static/o2c.html
flasgger/ui2/static/swagger-ui.js
flasgger/ui2/static/swagger-ui.min.js
flasgger/ui2/static/css/print.css
flasgger/ui2/static/css/reset.css
flasgger/ui2/static/css/screen.css
flasgger/ui2/static/css/style.css
flasgger/ui2/static/css/typography.css
flasgger/ui2/static/fonts/DroidSans-Bold.ttf
flasgger/ui2/static/fonts/DroidSans.ttf
flasgger/ui2/static/fonts/droid-sans-v6-latin-700.eot
flasgger/ui2/static/fonts/droid-sans-v6-latin-700.svg
flasgger/ui2/static/fonts/droid-sans-v6-latin-700.ttf
flasgger/ui2/static/fonts/droid-sans-v6-latin-700.woff
flasgger/ui2/static/fonts/droid-sans-v6-latin-700.woff2
flasgger/ui2/static/fonts/droid-sans-v6-latin-regular.eot
flasgger/ui2/static/fonts/droid-sans-v6-latin-regular.svg
flasgger/ui2/static/fonts/droid-sans-v6-latin-regular.ttf
flasgger/ui2/static/fonts/droid-sans-v6-latin-regular.woff
flasgger/ui2/static/fonts/droid-sans-v6-latin-regular.woff2
flasgger/ui2/static/images/collapse.gif
flasgger/ui2/static/images/expand.gif
flasgger/ui2/static/images/explorer_icons.png
flasgger/ui2/static/images/favicon-16x16.png
flasgger/ui2/static/images/favicon-32x32.png
flasgger/ui2/static/images/favicon.ico
flasgger/ui2/static/images/logo_small.png
flasgger/ui2/static/images/pet_store_api.png
flasgger/ui2/static/images/throbber.gif
flasgger/ui2/static/images/wordnik_api.png
flasgger/ui2/static/lang/ca.js
flasgger/ui2/static/lang/el.js
flasgger/ui2/static/lang/en.js
flasgger/ui2/static/lang/es.js
flasgger/ui2/static/lang/fr.js
flasgger/ui2/static/lang/geo.js
flasgger/ui2/static/lang/it.js
flasgger/ui2/static/lang/ja.js
flasgger/ui2/static/lang/ko-kr.js
flasgger/ui2/static/lang/pl.js
flasgger/ui2/static/lang/pt.js
flasgger/ui2/static/lang/ru.js
flasgger/ui2/static/lang/tr.js
flasgger/ui2/static/lang/translator.js
flasgger/ui2/static/lang/zh-cn.js
flasgger_tschaume-0.9.7.dist-info/LICENSE
flasgger_tschaume-0.9.7.dist-info/METADATA
flasgger_tschaume-0.9.7.dist-info/WHEEL
flasgger_tschaume-0.9.7.dist-info/entry_points.txt
flasgger_tschaume-0.9.7.dist-info/top_level.txt
flasgger_tschaume-0.9.7.dist-info/RECORD
