Metadata-Version: 2.1
Name: flasgger-tschaume
Version: 0.9.7
Summary: Extract swagger specs from your flask project
Home-page: https://github.com/tschaume/flasgger/
Author: Patrick Huck
Author-email: phuck@lbl.gov
License: MIT
Platform: any
Classifier: Intended Audience :: Developers
Classifier: Programming Language :: Python :: 3
Classifier: Programming Language :: Python :: 3.8
Classifier: Programming Language :: Python :: 3.9
Requires-Python: >=3.8
License-File: LICENSE
Requires-Dist: Flask (<2.3,>=0.10)
Requires-Dist: PyYAML (>=3.0)
Requires-Dist: jsonschema (>=3.0.1)
Requires-Dist: mistune
Requires-Dist: six (>=1.10.0)
Requires-Dist: werkzeug
Provides-Extra: dev
Requires-Dist: marshmallow ; extra == 'dev'
Requires-Dist: apispec (<6,>=1.0.0b5) ; extra == 'dev'
Requires-Dist: apispec-webframeworks ; extra == 'dev'
Requires-Dist: flask-restful ; extra == 'dev'
Requires-Dist: pep8 ; extra == 'dev'
Requires-Dist: flake8 ; extra == 'dev'
Requires-Dist: pytest (>=4.6) ; extra == 'dev'
Requires-Dist: flex ; extra == 'dev'
Requires-Dist: coveralls ; extra == 'dev'
Requires-Dist: pytest-cov ; extra == 'dev'
Requires-Dist: decorator ; extra == 'dev'
Requires-Dist: wheel ; extra == 'dev'
Requires-Dist: flask-jwt ; extra == 'dev'
Requires-Dist: readme-renderer ; extra == 'dev'
Requires-Dist: setuptools (>=40.4.2) ; extra == 'dev'
